zenius/__init__.py
zenius/smonline.py
zenius/vanisher.py
zenius-0.6.2.dist-info/METADATA
zenius-0.6.2.dist-info/WHEEL
zenius-0.6.2.dist-info/entry_points.txt
zenius-0.6.2.dist-info/licenses/LICENSE
zenius-0.6.2.dist-info/RECORD
