Metadata-Version: 2.4
Name: zenius
Version: 0.6.2
Summary: API for zenius simfile site
Author-email: Raeed Ahmed <code@raeed.me>
License-File: LICENSE
Requires-Python: <4,>=3.10
Requires-Dist: beautifulsoup4<5,>=4.12.3
Requires-Dist: iterfzf
Requires-Dist: loguru<0.8,>=0.7.2
Requires-Dist: lxml<6,>=5.1.0
Requires-Dist: questionary<3,>=2.0.1
Requires-Dist: requests<3,>=2.31.0
